jugri/__init__.py
jugri/_version.py
jugri/pandify.py
jugri/xify.py
jugri/tests/__init__.py
jugri/tests/test_pandify.py
jugri/tests/test_xify.py
jugri-0.5.2.dist-info/METADATA
jugri-0.5.2.dist-info/RECORD
jugri-0.5.2.dist-info/WHEEL
jugri-0.5.2.dist-info/top_level.txt
