Metadata-Version: 2.1
Name: jugri
Version: 0.5.2
Summary: JUGRI - The JUpyter - GRemlin Interface
Home-page: https://github.com/meltwater/jugri
Author: Laszlo Velinszky
Author-email: laszlo.velinszky@meltwater.com
License: ASL2
Platform: UNKNOWN
Classifier: Programming Language :: Python :: 3
Classifier: License :: OSI Approved :: Apache Software License
Classifier: Operating System :: OS Independent
